pybell/__init__.py
pybell/__main__.py
pybell/play_ding.py
pybell-0.1.0.dist-info/METADATA
pybell-0.1.0.dist-info/WHEEL
pybell-0.1.0.dist-info/top_level.txt
pybell-0.1.0.dist-info/RECORD
